[
  {
    "location": "Noble Park",
    "timestamp": "23/02/2026, 12:17:30 am",
    "count": 0
  },
  {
    "location": "Noble Park",
    "timestamp": "23/02/2026, 1:06:16 am",
    "count": 0
  },
  {
    "location": "Noble Park",
    "timestamp": "23/02/2026, 2:04:16 am",
    "count": 0
  },
  {
    "location": "Noble Park",
    "timestamp": "23/02/2026, 3:03:56 am",
    "count": 0
  },
  {
    "location": "Noble Park",
    "timestamp": "23/02/2026, 4:05:30 am",
    "count": 0
  },
  {
    "location": "Noble Park",
    "timestamp": "23/02/2026, 5:04:32 am",
    "count": 0
  }
]