[
  {
    "location": "Noble Park",
    "timestamp": "01/03/2026, 12:13:52 am",
    "count": 0
  },
  {
    "location": "Noble Park",
    "timestamp": "01/03/2026, 1:02:29 am",
    "count": 0
  },
  {
    "location": "Noble Park",
    "timestamp": "01/03/2026, 2:02:21 am",
    "count": 0
  },
  {
    "location": "Noble Park",
    "timestamp": "01/03/2026, 3:02:27 am",
    "count": 0
  },
  {
    "location": "Noble Park",
    "timestamp": "01/03/2026, 4:02:31 am",
    "count": 0
  },
  {
    "location": "Noble Park",
    "timestamp": "01/03/2026, 5:02:51 am",
    "count": 0
  },
  {
    "location": "Noble Park",
    "timestamp": "01/03/2026, 6:03:30 am",
    "count": 0
  },
  {
    "location": "Noble Park",
    "timestamp": "01/03/2026, 7:02:18 am",
    "count": 0
  },
  {
    "location": "Noble Park",
    "timestamp": "01/03/2026, 8:02:26 am",
    "count": 0
  },
  {
    "location": "Noble Park",
    "timestamp": "01/03/2026, 9:02:14 am",
    "count": 0
  },
  {
    "location": "Noble Park",
    "timestamp": "01/03/2026, 10:02:20 am",
    "count": 0
  },
  {
    "location": "Noble Park",
    "timestamp": "01/03/2026, 11:11:15 am",
    "count": 0
  }
]